{
    "students": [
        {
            "id": 2,
            "name": "张三",
            "gender": "0",
            "age": "18",
            "hobbies": "打游戏",
            "password": "123456"
        },
        {
            "name": "dawn",
            "gender": "0",
            "age": "18",
            "hobbies": "打游戏",
            "id": 4,
            "password": "315313"
        },
        {
            "name": "皮卡丘",
            "gender": "0",
            "age": "25",
            "hobbies": "睡觉，打豆豆",
            "password": "123456",
            "id": 5
        }
    ]
}